{
  "main": {
    "id": "755e7fdeea2d3340",
    "type": "split",
    "children": [
      {
        "id": "a6af5d5e2f271af1",
        "type": "tabs",
        "children": [
          {
            "id": "c7ec4e5ca02653f4",
            "type": "leaf",
            "state": {
              "type": "excalidraw",
              "state": {
                "file": "Excalidraw/GameLoop.md"
              },
              "icon": "excalidraw-icon",
              "title": "GameLoop"
            }
          },
          {
            "id": "a327c3262253d1c1",
            "type": "leaf",
            "state": {
              "type": "excalidraw",
              "state": {
                "file": "Excalidraw/SubmitCard Subroutine.md"
              },
              "icon": "excalidraw-icon",
              "title": "SubmitCard Subroutine"
            }
          }
        ],
        "currentTab": 1
      }
    ],
    "direction": "vertical"
  },
  "left": {
    "id": "964a919a69a47abd",
    "type": "split",
    "children": [
      {
        "id": "98a5ff3fbbd71c4b",
        "type": "tabs",
        "children": [
          {
            "id": "aa1a48a4fa467b54",
            "type": "leaf",
            "state": {
              "type": "file-explorer",
              "state": {
                "sortOrder": "alphabetical"
              },
              "icon": "lucide-folder-closed",
              "title": "Files"
            }
          },
          {
            "id": "7f440885f0d9f21b",
            "type": "leaf",
            "state": {
              "type": "search",
              "state": {
                "query": "colorchoi",
                "matchingCase": false,
                "explainSearch": false,
                "collapseAll": false,
                "extraContext": false,
                "sortOrder": "alphabetical"
              },
              "icon": "lucide-search",
              "title": "Search"
            }
          },
          {
            "id": "ef343a5513b86d83",
            "type": "leaf",
            "state": {
              "type": "bookmarks",
              "state": {},
              "icon": "lucide-bookmark",
              "title": "Bookmarks"
            }
          }
        ],
        "currentTab": 1
      }
    ],
    "direction": "horizontal",
    "width": 312.5026054382324,
    "collapsed": true
  },
  "right": {
    "id": "cdc6ec7b864c8510",
    "type": "split",
    "children": [
      {
        "id": "b1cbc5631877d12b",
        "type": "tabs",
        "children": [
          {
            "id": "5e2870b1629b7fa9",
            "type": "leaf",
            "state": {
              "type": "backlink",
              "state": {
                "file": "React Router/outlet.md",
                "collapseAll": false,
                "extraContext": false,
                "sortOrder": "alphabetical",
                "showSearch": false,
                "searchQuery": "",
                "backlinkCollapsed": false,
                "unlinkedCollapsed": true
              },
              "icon": "links-coming-in",
              "title": "Backlinks for outlet"
            }
          },
          {
            "id": "46eaf53bc6857001",
            "type": "leaf",
            "state": {
              "type": "outgoing-link",
              "state": {
                "file": "React Router/outlet.md",
                "linksCollapsed": false,
                "unlinkedCollapsed": true
              },
              "icon": "links-going-out",
              "title": "Outgoing links from outlet"
            }
          },
          {
            "id": "22968646f7682c9e",
            "type": "leaf",
            "state": {
              "type": "tag",
              "state": {
                "sortOrder": "frequency",
                "useHierarchy": true
              },
              "icon": "lucide-tags",
              "title": "Tags"
            }
          },
          {
            "id": "230cdee2f76e9b55",
            "type": "leaf",
            "state": {
              "type": "outline",
              "state": {
                "file": "React Router/outlet.md"
              },
              "icon": "lucide-list",
              "title": "Outline of outlet"
            }
          }
        ]
      }
    ],
    "direction": "horizontal",
    "width": 300,
    "collapsed": true
  },
  "left-ribbon": {
    "hiddenItems": {
      "switcher:Open quick switcher": false,
      "graph:Open graph view": false,
      "canvas:Create new canvas": false,
      "daily-notes:Open today's daily note": false,
      "templates:Insert template": false,
      "command-palette:Open command palette": false,
      "obsidian-excalidraw-plugin:Create new drawing": false
    }
  },
  "active": "a327c3262253d1c1",
  "lastOpenFiles": [
    "Server Events.md",
    "Excalidraw/GameLoop.md",
    "Excalidraw/SubmitCard Subroutine.md",
    "Excalidraw/Player Connection.md",
    "Client State.md",
    "Client Actions.md",
    "Excalidraw/Lobby Management Subroutine.md",
    "Types/Card.md",
    "Types/CardColor.md",
    "Types/ClientSidePlayer.md",
    "Types",
    "Excalidraw/HitDeck Subroutine.md",
    "Excalidraw/PickColor Subroutine.md",
    "Excalidraw/Choose Next Player Subroutine.md",
    "Excalidraw/ExcalidrawStartup.md",
    "Excalidraw",
    "Excalidraw",
    "UNO/Untitled.md",
    "React Router/switch.md",
    "React Router/outlet.md",
    "UNO",
    "Ask Others.md",
    "Profile Page.md",
    "React Router/nested routes.md",
    "React Router/demo App.jsx.md",
    "React Router/serving default error page.md",
    "React Router",
    "Welcome.md"
  ]
}